foam/__init__.py
foam/__main__.py
foam/app/__init__.py
foam/app/command/__init__.py
foam/app/command/adapter.py
foam/app/command/core.py
foam/app/information/__init__.py
foam/app/information/core.py
foam/app/postprocess/__init__.py
foam/app/postprocess/core.py
foam/base/__init__.py
foam/base/config.py
foam/base/core.py
foam/base/lib.py
foam/base/type.py
foam/compat/__init__.py
foam/compat/functools/__init__.py
foam/compat/functools/v37.py
foam/compat/shutil/__init__.py
foam/compat/shutil/v37.py
foam/compat/typing/__init__.py
foam/compat/typing/v37.py
foam/namespace/__init__.py
foam/namespace/brief.py
foam/namespace/full.py
foam/namespace/private.py
foam/parse/__init__.py
foam/parse/case.py
foam/parse/lark.py
foam/parse/static.py
foam/parse/url.py
foam/static/LICENSE.txt
foam/static/demo/7/cavity.yaml
foam/static/demo/8/cavity.yaml
foam/static/demo/9/cavity.yaml
foam/static/grammar/openfoam.lark
foam/util/__init__.py
foam/util/decorator.py
foam/util/function.py
foam/util/implementation.py
foam/util/object/__init__.py
foam/util/object/conversion.py
foam/util/object/data.py
foam/util/object/option.py
foam/util/object/popen.py
foam/util/object/result.py
foam/util/object/version.py
foam/util/private/__init__.py
foam/util/private/case.py
foam/util/private/email.py
foam/util/private/end.py
foam/util/private/figure/__init__.py
foam/util/private/figure/mpl.py
foam/util/private/figure/sns.py
foam/util/private/iterator.py
foam/util/private/timer.py
ifoam-0.13.5.dist-info/LICENSE.txt
ifoam-0.13.5.dist-info/WHEEL
ifoam-0.13.5.dist-info/METADATA
ifoam-0.13.5.dist-info/RECORD
