Metadata-Version: 2.1
Name: ifoam
Version: 0.13.5
Summary: Python Interface to OpenFOAM Case (Configured Using YAML)
Home-page: https://github.com/iydon/of.yaml
License: GPL-3.0-only
Keywords: OpenFOAM,YAML
Author: Iydon Liang
Author-email: liangiydon@gmail.com
Requires-Python: >=3.7,<4.0
Classifier: Environment :: Console
Classifier: License :: OSI Approved :: GNU General Public License v3 (GPLv3)
Classifier: Natural Language :: Chinese (Simplified)
Classifier: Natural Language :: English
Classifier: Operating System :: POSIX :: Linux
Classifier: Programming Language :: Python :: 3
Classifier: Programming Language :: Python :: 3.10
Classifier: Programming Language :: Python :: 3.7
Classifier: Programming Language :: Python :: 3.8
Classifier: Programming Language :: Python :: 3.9
Classifier: Topic :: Software Development :: User Interfaces
Classifier: Topic :: Utilities
Classifier: Typing :: Typed
Provides-Extra: 7z
Provides-Extra: cli
Provides-Extra: full
Provides-Extra: lark
Provides-Extra: mpl
Provides-Extra: toml
Provides-Extra: tqdm
Provides-Extra: type
Provides-Extra: vtk
Requires-Dist: PyYAML (>=6.0,<7.0)
Requires-Dist: click (>=8.0.3,<9.0.0); extra == "cli" or extra == "full"
Requires-Dist: lark (>=1.1.2,<2.0.0); extra == "lark" or extra == "full"
Requires-Dist: matplotlib (>=3.5.3,<4.0.0); extra == "mpl" or extra == "full"
Requires-Dist: nptyping (>=2.5.0,<3.0.0); extra == "type" or extra == "full"
Requires-Dist: py7zr (>=0.20.2,<0.21.0); extra == "7z" or extra == "full"
Requires-Dist: tomlkit (>=0.11.5,<0.12.0); extra == "toml" or extra == "full"
Requires-Dist: tqdm (>=4.63.1,<5.0.0); extra == "tqdm" or extra == "full"
Requires-Dist: typing-extensions (>=4.3.0,<5.0.0); extra == "type" or extra == "full"
Requires-Dist: vtk (>=9.1.0,<10.0.0); extra == "vtk" or extra == "full"
Project-URL: Bug Tracker, https://github.com/iydon/of.yaml/issues
Project-URL: Changes, https://github.com/iydon/of.yaml/blob/main/CHANGELOG.md
Project-URL: Documentation, https://ifoam.readthedocs.io
Project-URL: Repository, https://github.com/iydon/of.yaml
Project-URL: Template Project, https://github.com/iydon/of.yaml-template
Project-URL: Tutorial Project, https://github.com/iydon/of.yaml-tutorial
